population_data/Population_data.py
population_data/__init__.py
population_data-0.0.8.dist-info/METADATA
population_data-0.0.8.dist-info/WHEEL
population_data-0.0.8.dist-info/top_level.txt
population_data-0.0.8.dist-info/RECORD
