Metadata-Version: 2.1
Name: population-data
Version: 0.0.8
Summary: Get Population Data of the world
Home-page: https://techitutorial.com
Author: Anshu (Pydjango and techitutorials.com)
Author-email: <anshupal258@gmail.com>
License: UNKNOWN
Keywords: python,population,data,api,worldometer,population_data
Platform: UNKNOWN
Requires-Dist: requests
